rtl/memory.sv
module memory_vending ( 
    input logic clk,
    input logic rst,

    input logic [1:0] sel_item,

    input logic mem_read,
    input logic mem_write,

    output logic [7:0] price,
    output logic [7:0] stock
);
    import vending_pkg::*;

    logic [15:0] cafe, agua, suco, snack;

    // 1. Escrita síncrona na memória
    always_ff @(posedge clk) begin
        if (rst) begin
            cafe  <= {8'h19, 8'h05};
            agua  <= {8'h32, 8'h05};
            suco  <= {8'h4B, 8'h03};
            snack <= {8'h64, 8'h02};
        end else if (mem_write) begin
            case (item_t'(sel_item))
                CAFE:  cafe  <= cafe  - 1;
                AGUA:  agua  <= agua  - 1;
                SUCO:  suco  <= suco  - 1;
                SNACK: snack <= snack - 1;
            endcase
        end
    end

    // 2. Leitura Combinacional (Quebra o caminho síncrono ultra-rápido)
    always_comb begin
        if (mem_read) begin
            case (item_t'(sel_item)) 
                CAFE: begin
                    price = cafe[15:8];
                    stock = cafe[7:0];
                end
                AGUA: begin
                    price = agua[15:8];
                    stock = agua[7:0];
                end
                SUCO: begin
                    price = suco[15:8];
                    stock = suco[7:0];
                end
                SNACK: begin
                    price = snack[15:8];
                    stock = snack[7:0];
                end
                default: begin
                    price = 8'b0;
                    stock = 8'b0;
                end
            endcase
        end else begin
            price = 8'b0;
            stock = 8'b0;
        end
    end

endmodule

rtl/subtractor.sv
module subtractor (
    input logic [7:0] credit,
    input logic [7:0] price,

    output logic [7:0] change
);

    // Módulo puramente combinacional
    assign change = credit - price;

endmodule

rtl/comparator.sv
module comparator ( 
    input logic [7:0] credit,
    input logic [7:0] price,
    input logic [7:0] stock,

    output logic can_sell
);

    // Módulo puramente combinacional
    assign can_sell = (credit >= price) && (stock > 8'b0);


endmodule

rtl/credit_reg.sv
module credit_reg(
    // SINAIS VINDOS DO TOP MODULE
    input logic clk,
    input logic rst,
    input logic cancel,
    input logic [1:0] coin_in,  // Moeda que tá entrando, registrada em reg_coin_in

    // SINAIS DA CONTROL UNIT
    input logic credit_load,    // Sinal que aciona o registrador
    input logic credit_op,      // Determina se é pra acumular ou zerar

    output logic [7:0] credit // Valor acumulado

);

    // credit_load = 1 e FSM em COLLECT (op = 0): credit = credit + coin_value
    // credit_load = 1 e FSM em CHANGE (op = 1): credit = 0;

    logic [1:0] reg_coin_in; // coin_in registrado

    logic [7:0] registrador_credito;
    logic [7:0] coin_value;

    always_ff @(posedge clk) begin
        if(rst || cancel) begin
            reg_coin_in <= 2'b0;
            registrador_credito <= 8'b0;
        end else begin

            reg_coin_in <= coin_in;

            if (credit_load) begin
                if      (!credit_op) registrador_credito <= registrador_credito + coin_value;
                else if (credit_op)  registrador_credito <= 8'b0;
            end
        end
    end

    assign credit = registrador_credito;

    always_comb begin // Circuito combinacional responsável por decifrar qual o valor da moeda que tá entrando
        case (reg_coin_in) 
            2'b00: coin_value = 0; 
            2'b01: coin_value = 25;
            2'b10: coin_value = 50;
            2'b11: coin_value = 100;
            default: coin_value = 0;
        endcase
    end

endmodule

rtl/control_unit.sv
module control_unit (
    input logic clk,
    input logic rst,
    input logic confirm,
    input logic cancel,

    input logic [1:0] coin_in,

    output logic dispense,
    output logic error,

    output logic [2:0] state_out,

    // SINAIS INTERMÓDULOS

    input logic can_sell,           // Output do comparador

    output logic credit_load,       // Ativa registrador de crédito
    output logic credit_op,         // Operação a ser realizada pelo registrador de crédito 

    output logic mem_read,          // Ativa leitura da memória - price e stock
    output logic mem_write          // Ativa escrita da memória - decrementa stock

);

    import vending_pkg::*;

    state_t state;

    always_ff @(posedge clk) begin
        if (rst || cancel) begin
            state <= IDLE;
        end else begin
            case (state)
                IDLE: begin
                    if(coin_in != 2'b00) begin
                        state <= COLLECT; 
                    end
                end

                COLLECT: begin
                    if (confirm) begin
                        state <= CHECK_ACTIVATE_MEMORY;
                    end
                end

                CHECK_ACTIVATE_MEMORY: begin
                    state <= CHECK;
                end

                CHECK: begin
                    if (can_sell) begin
                        state <= DISPENSE;
                    end else begin
                        state <= ERROR;
                    end
                end

                DISPENSE: begin
                    state <= CHANGE_ACTIVATE_MEMORY;
                end

                CHANGE_ACTIVATE_MEMORY: begin
                    state <= CHANGE;
                end

                CHANGE: begin
                    state <= IDLE;
                end

                ERROR: begin
                    if (cancel) state <= IDLE;
                end

                default: begin
                    state <= IDLE;
                end

            endcase
        end
    end

    always_comb begin
        // Valores default para cada saída
        credit_load = 0;
        credit_op = 0;
        state_out = state;
        mem_read = 0;
        dispense = 0;
        mem_write = 0;
        error = 0;

        case (state)
            IDLE: begin
            end

            COLLECT: begin
                credit_load = 1;
                credit_op = 0;
            end

            CHECK_ACTIVATE_MEMORY: begin
                mem_read = 1;
            end

            CHECK: begin
                mem_read = 1;
            end

            DISPENSE: begin
                dispense = 1;
                mem_write = 1;
            end

            CHANGE_ACTIVATE_MEMORY: begin
                mem_read = 1;
            end

            CHANGE: begin
                credit_load = 1;
                credit_op = 1;
            end

            ERROR: begin
                error = 1;
            end

            default: begin // Evita latch implícito
                credit_load = 0;
                credit_op = 0;
                state_out = state;
                mem_read = 0;
                dispense = 0;
                mem_write = 0;
                error = 0;
            end

        endcase

    end

endmodule

rtl/vending_top.sv
module vending_top (
    input logic clk,
    input logic rst,
    input logic confirm,
    input logic cancel,

    input logic [1:0] coin_in,
    input logic [1:0] sel_item,

    output logic dispense,
    output logic error,
    output logic [7:0] change_out,
    output logic [7:0] display,
    output logic [2:0] state_out
);

    import vending_pkg::*;


    logic       wire_credit_load;
    logic       wire_credit_op;
    logic [7:0] wire_credit;
    logic       wire_can_sell;
    logic [7:0] wire_price;
    logic [7:0] wire_change;
    logic [7:0] wire_stock;
    logic       wire_mem_read;
    logic       wire_mem_write;

    assign display = wire_credit;

    control_unit cont_u (
        .clk(clk),
        .rst(rst),
        .confirm(confirm),
        .cancel(cancel),

        .coin_in(coin_in),

        .can_sell(wire_can_sell),

        .dispense(dispense),
        .error(error),

        .state_out(state_out),

        .credit_load(wire_credit_load),
        .credit_op(wire_credit_op),
        .mem_read(wire_mem_read),
        .mem_write(wire_mem_write)
    );

    credit_reg cred_r (
        .clk(clk),
        .rst(rst),
        .cancel(cancel),
        .coin_in(coin_in),

        .credit_load(wire_credit_load),
        .credit_op(wire_credit_op),
        
        .credit(wire_credit)
    );

    comparator comp (
        .credit(wire_credit),
        .price(wire_price),
        .stock(wire_stock),
        .can_sell(wire_can_sell)
    );

    subtractor sub (
        .credit(wire_credit),
        .price(wire_price),
        .change(wire_change)
    );

    memory_vending mem (
        .clk(clk),
        .rst(rst),
        .sel_item(sel_item),
        .mem_read(wire_mem_read),
        .mem_write(wire_mem_write),
        .price(wire_price),
        .stock(wire_stock)
    );

    always_comb begin
        if (state_out == CHANGE) begin
            change_out = wire_change;
        end else begin
            change_out = 8'b0;
        end
    end

endmodule

sim/tb_vending.sv
`timescale 1ns/1ps

module tb_vending;

    import vending_pkg::*;

    // Sinais do Testbench
    logic clk;
    logic rst;
    logic confirm;
    logic cancel;
    logic [1:0] coin_in;
    logic [1:0] sel_item;

    logic dispense;
    logic error;
    logic [7:0] change_out;
    logic [7:0] display;
    logic [2:0] state_out;

    // Sinais auxiliares para registrar eventos (pulso)
    logic dispense_triggered;
    logic error_triggered;
    logic [7:0] captured_change;

    // Instanciação do Vending Top
    vending_top uut (
        .clk(clk),
        .rst(rst),
        .confirm(confirm),
        .cancel(cancel),
        .coin_in(coin_in),
        .sel_item(sel_item),
        .dispense(dispense),
        .error(error),
        .change_out(change_out),
        .display(display),
        .state_out(state_out)
    );

    // 1. Geração de clock: always #5 clk = ~clk; (período 10 ns)
    always #5 clk = ~clk;

    // Captura de eventos transitórios
    always_ff @(posedge clk or posedge rst) begin
        if (rst) begin
            dispense_triggered <= 0;
            error_triggered    <= 0;
        end else begin
            if (dispense) dispense_triggered <= 1;
            if (error)    error_triggered    <= 1;
        end
    end

    // Captura o troco durante o estado de CHANGE
    always_comb begin
        if (state_out == CHANGE) begin
            captured_change = change_out;
        end
    end

    // 3. Tarefa apply_coin(value) que aplica uma moeda e aguarda 1 ciclo
    task apply_coin(input logic [1:0] value);
        begin
            @(posedge clk);
            coin_in <= value;
            @(posedge clk);
            coin_in <= 2'b00;
        end
    endtask

    // 4. Tarefa buy_item(item, coins[]) que executa uma compra completa
    task buy_item(input logic [1:0] item, input logic [1:0] coins[]);
        begin
            $display("[TB] Iniciando compra de item %0d...", item);
            dispense_triggered = 0;
            error_triggered = 0;
            captured_change = 0;
            sel_item = item;
            #10;
            foreach (coins[i]) begin
                apply_coin(coins[i]);
            end
            #10;
            // Pressiona confirm
            @(posedge clk);
            confirm <= 1;
            @(posedge clk);
            confirm <= 2'b0;
            
            // Aguarda conclusão (IDLE ou ERROR)
            wait(state_out == IDLE || state_out == ERROR);
            #1; // Pequena margem de tempo para propagação das saídas
            if (state_out == ERROR) begin
                $display("[TB] Compra falhou (FSM em estado ERROR).");
                @(posedge clk);
                cancel <= 1;
                @(posedge clk);
                cancel <= 0;
                wait(state_out == IDLE);
            end else begin
                $display("[TB] Compra concluída com sucesso.");
            end
            #10;
        end
    endtask

    // 5. Tarefa check(expected, actual, label) que reporta PASS/FAIL
    task check(input logic [31:0] expected, input logic [31:0] actual, input string label);
        begin
            if (expected === actual) begin
                $display("[PASS] %s | Esperado: %0d, Obtido: %0d", label, expected, actual);
            end else begin
                $display("[FAIL] %s | Esperado: %0d, Obtido: %0d", label, expected, actual);
            end
        end
    endtask

    // Procedimento de Teste
    initial begin
        // Inicializações
        clk = 0;
        rst = 0;
        confirm = 0;
        cancel = 0;
        coin_in = 2'b00;
        sel_item = 2'b00;

        $display("==================================================");
        $display("Iniciando Testbench de tb_vending");
        $display("==================================================");

        // 2. Reset inicial por 2 ciclos de clock
        $display("[TB] Aplicando Reset por 2 ciclos de clock...");
        rst = 1;
        repeat(2) @(posedge clk);
        rst = 0;
        @(posedge clk);
        check(IDLE, state_out, "Verificação de Reset");

        // Caso de teste 1: Comprar Cafe (Preço 25) com exatamente 25
        $display("\n--- Caso de Teste 1: Comprar Cafe com valor exato (25) ---");
        buy_item(CAFE, '{2'b01});
        check(1, dispense_triggered, "Dispense do Café");
        check(0, error_triggered, "Error Status do Café");
        check(0, captured_change, "Troco do Café (esperado 0)");

        // Caso de teste 2: Comprar Agua (Preço 50) com 100 (troco de 50)
        $display("\n--- Caso de Teste 2: Comprar Agua com troco (100 -> troco 50) ---");
        buy_item(AGUA, '{2'b11});
        check(1, dispense_triggered, "Dispense da Água");
        check(0, error_triggered, "Error Status da Água");
        check(50, captured_change, "Troco da Água (esperado 50)");

        // Caso de teste 3: Tentativa de compra com saldo insuficiente (Suco Preço 75, pagando 50)
        $display("\n--- Caso de Teste 3: Compra com saldo insuficiente (Suco, pagando 50) ---");
        buy_item(SUCO, '{2'b10});
        check(0, dispense_triggered, "Dispense do Suco (esperado 0)");
        check(1, error_triggered, "Error Status do Suco (esperado 1)");

        $display("==================================================");
        $display("Fim da Simulação!");
        $display("==================================================");
        $finish;
    end

    // 6. Geração de waveform;
    initial begin
        $dumpfile("waves.vcd");
        $dumpvars(0, tb_vending);
    end

    // Monitor para depuração
    always @(posedge clk) begin
        $display("[CLK %0t] state=%0d coin_in=%b reg_coin_in=%b coin_val=%0d display=%0d confirm=%b cancel=%b dispense=%b error=%b change_out=%0d", 
                 $time, state_out, coin_in, uut.cred_r.reg_coin_in, uut.cred_r.coin_value, display, confirm, cancel, dispense, error, change_out);
    end

endmodule

waves.vcd
$date
	Fri Jul 10 03:29:26 2026
$end
$version
	Icarus Verilog
$end
$timescale
	1ps
$end
$scope module tb_vending $end
$var wire 3 ! state_out [2:0] $end
$var wire 1 " error $end
$var wire 8 # display [7:0] $end
$var wire 1 $ dispense $end
$var wire 8 % change_out [7:0] $end
$var reg 1 & cancel $end
$var reg 8 ' captured_change [7:0] $end
$var reg 1 ( clk $end
$var reg 2 ) coin_in [1:0] $end
$var reg 1 * confirm $end
$var reg 1 + dispense_triggered $end
$var reg 1 , error_triggered $end
$var reg 1 - rst $end
$var reg 2 . sel_item [1:0] $end
$scope module uut $end
$var wire 1 & cancel $end
$var wire 1 ( clk $end
$var wire 2 / coin_in [1:0] $end
$var wire 1 * confirm $end
$var wire 8 0 display [7:0] $end
$var wire 1 - rst $end
$var wire 2 1 sel_item [1:0] $end
$var wire 8 2 wire_stock [7:0] $end
$var wire 8 3 wire_price [7:0] $end
$var wire 1 4 wire_mem_write $end
$var wire 1 5 wire_mem_read $end
$var wire 1 6 wire_credit_op $end
$var wire 1 7 wire_credit_load $end
$var wire 8 8 wire_credit [7:0] $end
$var wire 8 9 wire_change [7:0] $end
$var wire 1 : wire_can_sell $end
$var wire 3 ; state_out [2:0] $end
$var wire 1 " error $end
$var wire 1 $ dispense $end
$var reg 8 < change_out [7:0] $end
$scope module comp $end
$var wire 1 : can_sell $end
$var wire 8 = stock [7:0] $end
$var wire 8 > price [7:0] $end
$var wire 8 ? credit [7:0] $end
$upscope $end
$scope module cont_u $end
$var wire 1 : can_sell $end
$var wire 1 & cancel $end
$var wire 1 ( clk $end
$var wire 2 @ coin_in [1:0] $end
$var wire 1 * confirm $end
$var wire 1 - rst $end
$var reg 1 7 credit_load $end
$var reg 1 6 credit_op $end
$var reg 1 $ dispense $end
$var reg 1 " error $end
$var reg 1 5 mem_read $end
$var reg 1 4 mem_write $end
$var reg 3 A state [2:0] $end
$var reg 3 B state_out [2:0] $end
$upscope $end
$scope module cred_r $end
$var wire 1 & cancel $end
$var wire 1 ( clk $end
$var wire 2 C coin_in [1:0] $end
$var wire 1 7 credit_load $end
$var wire 1 6 credit_op $end
$var wire 1 - rst $end
$var wire 8 D credit [7:0] $end
$var reg 8 E coin_value [7:0] $end
$var reg 2 F reg_coin_in [1:0] $end
$var reg 8 G registrador_credito [7:0] $end
$upscope $end
$scope module mem $end
$var wire 1 ( clk $end
$var wire 1 5 mem_read $end
$var wire 1 4 mem_write $end
$var wire 1 - rst $end
$var wire 2 H sel_item [1:0] $end
$var reg 16 I agua [15:0] $end
$var reg 16 J cafe [15:0] $end
$var reg 8 K price [7:0] $end
$var reg 16 L snack [15:0] $end
$var reg 8 M stock [7:0] $end
$var reg 16 N suco [15:0] $end
$upscope $end
$scope module sub $end
$var wire 8 O credit [7:0] $end
$var wire 8 P price [7:0] $end
$var wire 8 Q change [7:0] $end
$upscope $end
$upscope $end
$scope task apply_coin $end
$var reg 2 R value [1:0] $end
$upscope $end
$scope task buy_item $end
$var reg 2 S item [1:0] $end
$scope begin $ivl_foreach0 $end
$var integer 32 T i [31:0] $end
$upscope $end
$upscope $end
$scope task check $end
$var reg 32 U actual [31:0] $end
$var reg 32 V expected [31:0] $end
$upscope $end
$upscope $end
$enddefinitions $end
$comment Show the parameter values. $end
$dumpall
$end
#0
$dumpvars
bx V
bx U
b0 T
bx S
bx R
bx Q
bx P
bx O
bx N
bx M
bx L
bx K
bx J
bx I
b0 H
bx G
bx F
b0 E
bx D
b0 C
bx B
bx A
b0 @
bx ?
bx >
bx =
b0 <
bx ;
x:
bx 9
bx 8
07
06
05
04
bx 3
bx 2
b0 1
bx 0
b0 /
b0 .
1-
0,
0+
0*
b0 )
0(
bx '
0&
b0 %
0$
bx #
0"
bx !
$end
#5000
b0 !
b0 ;
b0 B
b0 A
b0 #
b0 0
b0 8
b0 ?
b0 D
b0 G
b0 O
b0 F
b110010000000010 L
b100101100000011 N
b11001000000101 I
b1100100000101 J
1(
#10000
0(
#15000
0-
1(
#20000
0(
#25000
0:
b0 2
b0 =
b0 M
b0 9
b0 Q
b0 3
b0 >
b0 K
b0 P
b0 '
b0 S
b0 U
b0 V
1(
#30000
0(
#35000
b1 )
b1 /
b1 @
b1 C
1(
b1 R
#40000
0(
#45000
17
b1 !
b1 ;
b1 B
b11001 E
b0 )
b0 /
b0 @
b0 C
b1 A
b1 F
b1 T
1(
#50000
0(
#55000
b0 E
b11001 9
b11001 Q
b11001 #
b11001 0
b11001 8
b11001 ?
b11001 D
b11001 G
b11001 O
b0 F
1*
1(
#60000
0(
#65000
15
b110 !
b110 ;
b110 B
07
0*
b110 A
1(
#70000
0(
#75000
1:
15
b10 !
b10 ;
b10 B
b101 2
b101 =
b101 M
b0 9
b0 Q
b11001 3
b11001 >
b11001 K
b11001 P
b10 A
1(
#80000
0(
#85000
14
1$
05
b11 !
b11 ;
b11 B
b11 A
1(
#90000
0(
#95000
15
04
0$
b111 !
b111 ;
b111 B
b1100100000100 J
b111 A
1+
1(
#100000
0(
#105000
16
17
05
b100 !
b100 ;
b100 B
b100 A
b100 2
b100 =
b100 M
1(
#110000
0(
#115000
0:
b0 !
b0 ;
b0 B
06
07
b0 2
b0 =
b0 M
b0 3
b0 >
b0 K
b0 P
b0 9
b0 Q
b0 #
b0 0
b0 8
b0 ?
b0 D
b0 G
b0 O
b0 A
1(
#120000
0(
#125000
1(
#126000
b1 .
b1 1
b1 H
0+
b1 S
b0 U
b0 V
#130000
0(
#135000
1(
#136000
b11 R
b0 T
#140000
0(
#145000
b11 )
b11 /
b11 @
b11 C
1(
#150000
0(
#155000
b1100100 E
17
b1 !
b1 ;
b1 B
b0 )
b0 /
b0 @
b0 C
b11 F
b1 A
b1 T
1(
#160000
0(
#165000
b0 E
b1100100 9
b1100100 Q
b1100100 #
b1100100 0
b1100100 8
b1100100 ?
b1100100 D
b1100100 G
b1100100 O
b0 F
1*
1(
#170000
0(
#175000
15
b110 !
b110 ;
b110 B
07
0*
b110 A
1(
#180000
0(
#185000
15
b10 !
b10 ;
b10 B
1:
b10 A
b101 2
b101 =
b101 M
b110010 9
b110010 Q
b110010 3
b110010 >
b110010 K
b110010 P
1(
#190000
0(
#195000
14
1$
05
b11 !
b11 ;
b11 B
b11 A
1(
#200000
0(
#205000
15
04
0$
b111 !
b111 ;
b111 B
b111 A
b11001000000100 I
1+
1(
#210000
0(
#215000
b110010 '
b110010 %
b110010 <
16
17
05
b100 !
b100 ;
b100 B
b100 2
b100 =
b100 M
b100 A
1(
#220000
0(
#225000
b0 !
b0 ;
b0 B
06
07
0:
b0 %
b0 <
b0 A
b0 #
b0 0
b0 8
b0 ?
b0 D
b0 G
b0 O
b0 2
b0 =
b0 M
b0 9
b0 Q
b0 3
b0 >
b0 K
b0 P
1(
#230000
0(
#235000
1(
#236000
b10 .
b10 1
b10 H
b0 '
0+
b10 S
b110010 U
b110010 V
#240000
0(
#245000
1(
#246000
b10 R
b0 T
#250000
0(
#255000
b10 )
b10 /
b10 @
b10 C
1(
#260000
0(
#265000
17
b1 !
b1 ;
b1 B
b110010 E
b0 )
b0 /
b0 @
b0 C
b1 A
b10 F
b1 T
1(
#270000
0(
#275000
b0 E
b110010 9
b110010 Q
b110010 #
b110010 0
b110010 8
b110010 ?
b110010 D
b110010 G
b110010 O
b0 F
1*
1(
#280000
0(
#285000
15
b110 !
b110 ;
b110 B
07
0*
b110 A
1(
#290000
0(
#295000
15
b10 !
b10 ;
b10 B
b11 2
b11 =
b11 M
b11100111 9
b11100111 Q
b1001011 3
b1001011 >
b1001011 K
b1001011 P
b10 A
1(
#300000
0(
#305000
1"
05
b101 !
b101 ;
b101 B
b101 A
1(
#310000
0(
#315000
b0 2
b0 =
b0 M
b110010 9
b110010 Q
b0 3
b0 >
b0 K
b0 P
1&
1,
1(
#320000
0(
#325000
0"
b0 !
b0 ;
b0 B
0&
b0 A
b0 9
b0 Q
b0 #
b0 0
b0 8
b0 ?
b0 D
b0 G
b0 O
1(
#330000
0(
#335000
1(
b1 U
b1 V
